mezon/__init__.py
mezon/client.py
mezon/models.py
mezon/session.py
mezon/api/__init__.py
mezon/api/mezon_api.py
mezon/api/utils.py
mezon/constants/__init__.py
mezon/constants/enum.py
mezon/constants/rate_limit.py
mezon/managers/__init__.py
mezon/managers/cache.py
mezon/managers/channel.py
mezon/managers/event.py
mezon/managers/session.py
mezon/managers/socket.py
mezon/messages/__init__.py
mezon/messages/db.py
mezon/protobuf/__init__.py
mezon/protobuf/utils.py
mezon/protobuf/api/api_pb2.py
mezon/protobuf/api/api_pb2.pyi
mezon/protobuf/rtapi/realtime_pb2.py
mezon/protobuf/rtapi/realtime_pb2.pyi
mezon/socket/__init__.py
mezon/socket/default_socket.py
mezon/socket/message_builder.py
mezon/socket/promise_executor.py
mezon/socket/websocket_adapter.py
mezon/structures/__init__.py
mezon/structures/button_builder.py
mezon/structures/clan.py
mezon/structures/interactive_message.py
mezon/structures/message.py
mezon/structures/text_channel.py
mezon/structures/user.py
mezon/utils/__init__.py
mezon/utils/helper.py
mezon/utils/logger.py
mezon_sdk-1.6.8.dist-info/licenses/LICENSE
mezon_sdk-1.6.8.dist-info/METADATA
mezon_sdk-1.6.8.dist-info/WHEEL
mezon_sdk-1.6.8.dist-info/top_level.txt
mezon_sdk-1.6.8.dist-info/RECORD
