Metadata-Version: 2.4
Name: mezon-sdk
Version: 1.6.8
Summary: Mezon Python SDK - A Python implementation of the Mezon TypeScript SDK
License-Expression: Apache-2.0
Project-URL: Homepage, https://github.com/phuvinh010701/mezon-sdk-python
Project-URL: Issues, https://github.com/phuvinh010701/mezon-sdk-python/issues
Requires-Python: >=3.13
License-File: LICENSE
Requires-Dist: pydantic>=2.12.3
Requires-Dist: aiohttp>=3.9.0
Requires-Dist: websockets>=12.0
Requires-Dist: protobuf>=4.25.0
Requires-Dist: pyjwt>=2.8.0
Requires-Dist: aiosqlite>=0.20.0
Requires-Dist: mmn-sdk==1.0.0
Requires-Dist: aiolimiter>=1.2.1
Requires-Dist: tenacity>=9.1.2
Dynamic: license-file
